neospaceai/__init__.py
neospaceai/manager.py
neospaceai/report.py
neospaceai-0.2.3.dist-info/METADATA
neospaceai-0.2.3.dist-info/WHEEL
neospaceai-0.2.3.dist-info/top_level.txt
neospaceai-0.2.3.dist-info/RECORD
